aistudio_scheduler_lock/__init__.py
aistudio_scheduler_lock/admin.py
aistudio_scheduler_lock/apps.py
aistudio_scheduler_lock/locks/base_lock.py
aistudio_scheduler_lock/locks/database_advisory_lock.py
aistudio_scheduler_lock/locks/database_lock.py
aistudio_scheduler_lock/locks/file_lock.py
aistudio_scheduler_lock/locks/utils.py
aistudio_scheduler_lock/migrations/0001_initial.py
aistudio_scheduler_lock/migrations/__init__.py
aistudio_scheduler_lock/models.py
aistudio_scheduler_lock/schedules/enums.py
aistudio_scheduler_lock/schedules/scheduler_lock_job.py
aistudio_scheduler_lock/schedules/schedules_master_base.py
aistudio_scheduler_lock/tests.py
aistudio_scheduler_lock-1.0.8.dist-info/METADATA
aistudio_scheduler_lock-1.0.8.dist-info/WHEEL
aistudio_scheduler_lock-1.0.8.dist-info/RECORD
