Metadata-Version: 2.1
Name: aistudio-scheduler-lock
Version: 1.0.8
Summary: Implements a distributed locking scheme for schedulers running on HA mode.
Author: Yogesh Ketkar
Author-email: yogesh.ketkar@automationedge.com
Requires-Python: >=3.9,<4.0
Classifier: Programming Language :: Python :: 3
Classifier: Programming Language :: Python :: 3.9
Classifier: Programming Language :: Python :: 3.10
Classifier: Programming Language :: Python :: 3.11
Requires-Dist: Django (>=3.2.20,<4.0.0)
Requires-Dist: django-apscheduler (==0.6.2)
Requires-Dist: setuptools (==65.5.1)
